{"cameraMode":{"drawMode":0,"name":"Shaded","section":"Shading Mode"},"sceneLighting":true,"audioPlay":false,"sceneViewState":{"m_AlwaysRefresh":false,"showFog":true,"showSkybox":true,"showFlares":true,"showImageEffects":true,"showParticleSystems":true,"showVisualEffectGraphs":true,"m_FxEnabled":true},"in2DMode":false,"pivot":{"x":482.3915100097656,"y":-2.9185562133789064,"z":510.6440734863281},"rotation":{"x":-0.18740975856781007,"y":0.7070333361625671,"z":-0.2037741094827652,"w":-0.6508226990699768},"size":50.48960876464844,"orthographic":false}